contcfg/__init__.py
contcfg/main.py
contcfg/cmd_wrapper/__init__.py
contcfg/cmd_wrapper/base.py
contcfg/cmd_wrapper/dockercmd_wrapper.py
contcfg/cmd_wrapper/exception.py
contcfg/cmd_wrapper/tc_base.py
contcfg/cmd_wrapper/tccmd_wrapper.py
contcfg/container_net_ctrl/__init__.py
contcfg/container_net_ctrl/comm.py
contcfg/container_net_ctrl/container_net_controller.py
contcfg/container_net_ctrl/container_net_server.py
contcfg/container_net_ctrl/msg.py
contcfg/utils/scripts/clear_tc_rules.sh
contcfg/utils/scripts/docker_tcconfig.sh
contcfg/utils/scripts/find_container_ip.sh
contcfg/utils/scripts/find_container_veth_name.sh
contcfg/utils/scripts/functions.sh
contcfg/utils/scripts/set_network_limit.sh
contcfg-0.0.5.dist-info/LICENSE.txt
contcfg-0.0.5.dist-info/METADATA
contcfg-0.0.5.dist-info/WHEEL
contcfg-0.0.5.dist-info/entry_points.txt
contcfg-0.0.5.dist-info/top_level.txt
contcfg-0.0.5.dist-info/RECORD
