Metadata-Version: 2.2
Name: contcfg
Version: 0.0.5
Summary: A simple tools for container network configuration using tc command.
Author-email: DeEMO <yzzxrx@gmail.com>
Maintainer-email: DeEMO <yzzxrx@gmail.com>
License: Copyright (c) 2016 The Python Packaging Authority (PyPA)
Classifier: Development Status :: 3 - Alpha
Classifier: Intended Audience :: Developers
Classifier: License :: OSI Approved :: MIT License
Classifier: Programming Language :: Python :: 3
Classifier: Programming Language :: Python :: 3.8
Classifier: Programming Language :: Python :: 3.9
Classifier: Programming Language :: Python :: 3.10
Classifier: Programming Language :: Python :: 3.11
Classifier: Programming Language :: Python :: 3.12
Classifier: Programming Language :: Python :: 3 :: Only
Requires-Python: >=3.9
License-File: LICENSE.txt
Provides-Extra: dev
Requires-Dist: check-manifest; extra == "dev"
Provides-Extra: test
Requires-Dist: coverage; extra == "test"
